README.md
setup.py
spt_datascience/__init__.py
spt_datascience/credentials.py
spt_datascience/factory.py
spt_datascience/resources.py
spt_datascience.egg-info/PKG-INFO
spt_datascience.egg-info/SOURCES.txt
spt_datascience.egg-info/dependency_links.txt
spt_datascience.egg-info/requires.txt
spt_datascience.egg-info/top_level.txt
spt_datascience/datascience/__init__.py
spt_datascience/datascience/data_vault.py
spt_datascience/datascience/model_manager.py
spt_datascience/datascience/model_util.py
spt_datascience/datascience/models_storage.py
spt_datascience/datascience/pipeline_manager.py
spt_datascience/datascience/singleton.py
spt_datascience/datascience/models/__init__.py
spt_datascience/datascience/models/base_model.py
spt_datascience/datascience/models/estimator_model.py
spt_datascience/datascience/models/rest_model.py
spt_datascience/datascience/pipelines/__init__.py
spt_datascience/datascience/pipelines/base_pipeline.py