Metadata-Version: 2.1
Name: spt-datascience
Version: 0.0.9
Summary: SPT ds manager
Home-page: UNKNOWN
Author: Mark Poroshin
Author-email: mporoshin@smartpredictiontech.ru
License: UNKNOWN
Platform: UNKNOWN
Classifier: Development Status :: 4 - Beta
Classifier: Intended Audience :: Developers
Classifier: Topic :: Software Development :: Build Tools
Classifier: License :: OSI Approved :: MIT License
Classifier: Programming Language :: Python :: 3.7
Classifier: Programming Language :: Python :: 3.8
Classifier: Programming Language :: Python :: 3.9
